cli/__init__.py
docker_cli/__init__.py
porter/__init__.py
porter_cli-1.0.6.dist-info/METADATA
porter_cli-1.0.6.dist-info/WHEEL
porter_cli-1.0.6.dist-info/dependency_links.txt
porter_cli-1.0.6.dist-info/entry_points.txt
porter_cli-1.0.6.dist-info/top_level.txt
porter_cli-1.0.6.dist-info/RECORD
