Metadata-Version: 2.1
Name: porter-cli
Version: 1.0.6
Summary: A simple command line app for managing and deploying taps projects
Home-page: https://github.com/portermetrics/porter_cli
Author: Carlos Alexis Gomez Ruiz
Author-email: alexis@portermetrics.com
License: Proprietary License
Download-URL: https://github.com/portermetrics/porter_cli/archive/1.0.0.tar.gz
Platform: UNKNOWN
Classifier: License :: Other/Proprietary License
Classifier: Programming Language :: Python :: 3.8
Requires-Python: >=3.8
Requires-Dist: chalice
Requires-Dist: click (<8.0,>=7)
Requires-Dist: botocore
